generate_completions.sh
tldr_man/__init__.py
tldr_man/__main__.py
tldr_man/color.py
tldr_man/errors.py
tldr_man/languages.py
tldr_man/main.py
tldr_man/pages.py
tldr_man/platforms.py
tldr_man/shell_completion.py
tldr_man/temp_path.py
tldr-man.1
tldr_man-1.5.2.dist-info/LICENSE
tldr_man-1.5.2.dist-info/METADATA
tldr_man-1.5.2.dist-info/WHEEL
tldr_man-1.5.2.dist-info/entry_points.txt
tldr_man-1.5.2.dist-info/RECORD
