Metadata-Version: 2.1
Name: tldr-man
Version: 1.5.2
Summary: Command-line TLDR client that displays tldr-pages as manpages
Home-page: https://tldr-man.superatomic.dev/
License: Apache-2.0
Keywords: tldr,tldr-pages,man,manpage,tldr-client
Author: Olivia Kinnear
Author-email: contact@superatomic.dev
Requires-Python: >=3.10.4,<4.0.0
Classifier: Development Status :: 5 - Production/Stable
Classifier: Environment :: Console
Classifier: Intended Audience :: Developers
Classifier: Intended Audience :: End Users/Desktop
Classifier: Intended Audience :: System Administrators
Classifier: License :: OSI Approved :: Apache Software License
Classifier: Natural Language :: English
Classifier: Operating System :: MacOS
Classifier: Operating System :: POSIX
Classifier: Operating System :: POSIX :: Linux
Classifier: Operating System :: POSIX :: SunOS/Solaris
Classifier: Operating System :: Unix
Classifier: Programming Language :: Python :: 3
Classifier: Programming Language :: Python :: 3.11
Classifier: Programming Language :: Python :: 3.12
Classifier: Programming Language :: Unix Shell
Classifier: Topic :: Documentation
Classifier: Topic :: Software Development :: Documentation
Classifier: Topic :: Text Processing :: Markup :: Markdown
Classifier: Topic :: Utilities
Requires-Dist: click (>=8.1.7,<9.0.0)
Requires-Dist: click-help-colors (>=0.9.4,<0.10.0)
Requires-Dist: filelock (>=3.12.3,<4.0.0)
Requires-Dist: requests (>=2.28.1,<3.0.0)
Project-URL: Bug Tracker, https://github.com/superatomic/tldr-man/issues
Project-URL: Documentation, https://github.com/superatomic/tldr-man#readme
Project-URL: Repository, https://github.com/superatomic/tldr-man
